llmpdf/__init__.py
llmpdf/ai.py
llmpdf/db.py
llmpdf/download.py
llmpdf/main.py
llmpdf/util.py
llm_pdf_chat-0.5.0.dist-info/LICENSE
llm_pdf_chat-0.5.0.dist-info/METADATA
llm_pdf_chat-0.5.0.dist-info/WHEEL
llm_pdf_chat-0.5.0.dist-info/entry_points.txt
llm_pdf_chat-0.5.0.dist-info/RECORD
